minestat/__init__.py
minestat/py.typed
minestat-2.6.3.dist-info/LICENSE.txt
minestat-2.6.3.dist-info/METADATA
minestat-2.6.3.dist-info/WHEEL
minestat-2.6.3.dist-info/top_level.txt
minestat-2.6.3.dist-info/RECORD
