Metadata-Version: 2.1
Name: minestat
Version: 2.6.3
Summary: A Minecraft server status checker
Home-page: https://github.com/FragLand/minestat
Author: Lloyd Dilley and Felix Ern (MindSolve)
Author-email: minecraft@frag.land
Classifier: Programming Language :: Python :: 3
Classifier: License :: OSI Approved :: GNU General Public License v3 (GPLv3)
Classifier: Operating System :: OS Independent
Classifier: Topic :: Games/Entertainment
Classifier: Topic :: Software Development :: Libraries :: Python Modules
Classifier: Topic :: System :: Networking :: Monitoring
Classifier: Topic :: Utilities
Requires-Python: >=3.6
License-File: LICENSE.txt
Requires-Dist: dnspython <2.7.0,>=2.2.1
